gitactiontest/__init__.py
gitactiontest/hello.py
gitactiontest-1.0.3.dist-info/METADATA
gitactiontest-1.0.3.dist-info/WHEEL
gitactiontest-1.0.3.dist-info/top_level.txt
gitactiontest-1.0.3.dist-info/RECORD
